package com.google.android.gms.internal;

class bq
  implements Runnable
{
  bq(bp parambp, bo parambo)
  {
  }

  // ERROR //
  public void run()
  {
    // Byte code:
    //   0: aload_0
    //   1: getfield 14	com/google/android/gms/internal/bq:b	Lcom/google/android/gms/internal/bp;
    //   4: invokestatic 25	com/google/android/gms/internal/bp:a	(Lcom/google/android/gms/internal/bp;)Ljava/lang/Object;
    //   7: astore_1
    //   8: aload_1
    //   9: monitorenter
    //   10: aload_0
    //   11: getfield 14	com/google/android/gms/internal/bq:b	Lcom/google/android/gms/internal/bp;
    //   14: invokestatic 28	com/google/android/gms/internal/bp:b	(Lcom/google/android/gms/internal/bp;)I
    //   17: bipush 254
    //   19: if_icmpeq +8 -> 27
    //   22: aload_1
    //   23: monitorexit
    //   24: goto +70 -> 94
    //   27: aload_0
    //   28: getfield 14	com/google/android/gms/internal/bq:b	Lcom/google/android/gms/internal/bp;
    //   31: aload_0
    //   32: getfield 14	com/google/android/gms/internal/bq:b	Lcom/google/android/gms/internal/bp;
    //   35: invokestatic 32	com/google/android/gms/internal/bp:c	(Lcom/google/android/gms/internal/bp;)Lcom/google/android/gms/internal/by;
    //   38: invokestatic 35	com/google/android/gms/internal/bp:a	(Lcom/google/android/gms/internal/bp;Lcom/google/android/gms/internal/by;)Lcom/google/android/gms/internal/by;
    //   41: pop
    //   42: aload_0
    //   43: getfield 14	com/google/android/gms/internal/bq:b	Lcom/google/android/gms/internal/bp;
    //   46: invokestatic 38	com/google/android/gms/internal/bp:d	(Lcom/google/android/gms/internal/bp;)Lcom/google/android/gms/internal/by;
    //   49: ifnonnull +21 -> 70
    //   52: aload_0
    //   53: getfield 14	com/google/android/gms/internal/bq:b	Lcom/google/android/gms/internal/bp;
    //   56: iconst_4
    //   57: invokevirtual 41	com/google/android/gms/internal/bp:a	(I)V
    //   60: aload_1
    //   61: monitorexit
    //   62: goto +32 -> 94
    //   65: astore_2
    //   66: aload_1
    //   67: monitorexit
    //   68: aload_2
    //   69: athrow
    //   70: aload_0
    //   71: getfield 16	com/google/android/gms/internal/bq:a	Lcom/google/android/gms/internal/bo;
    //   74: aload_0
    //   75: getfield 14	com/google/android/gms/internal/bq:b	Lcom/google/android/gms/internal/bp;
    //   78: invokevirtual 46	com/google/android/gms/internal/bo:a	(Lcom/google/android/gms/internal/bs;)V
    //   81: aload_0
    //   82: getfield 14	com/google/android/gms/internal/bq:b	Lcom/google/android/gms/internal/bp;
    //   85: aload_0
    //   86: getfield 16	com/google/android/gms/internal/bq:a	Lcom/google/android/gms/internal/bo;
    //   89: invokestatic 48	com/google/android/gms/internal/bp:a	(Lcom/google/android/gms/internal/bp;Lcom/google/android/gms/internal/bo;)V
    //   92: aload_1
    //   93: monitorexit
    //   94: return
    //
    // Exception table:
    //   from	to	target	type
    //   10	68	65	finally
    //   70	94	65	finally
  }
}

/* Location:           M:\Google Play\APKtoJava_RC2\tools\classes-dex2jar.jar
 * Qualified Name:     com.google.android.gms.internal.bq
 * JD-Core Version:    0.6.0
 */