package com.google.android.gms.internal;

class ew
  implements Runnable
{
  ew(es parames)
  {
  }

  // ERROR //
  public void run()
  {
    // Byte code:
    //   0: aload_0
    //   1: getfield 12	com/google/android/gms/internal/ew:a	Lcom/google/android/gms/internal/es;
    //   4: invokestatic 21	com/google/android/gms/internal/es:a	(Lcom/google/android/gms/internal/es;)Ljava/lang/Object;
    //   7: astore_1
    //   8: aload_1
    //   9: monitorenter
    //   10: aload_0
    //   11: getfield 12	com/google/android/gms/internal/ew:a	Lcom/google/android/gms/internal/es;
    //   14: invokestatic 25	com/google/android/gms/internal/es:c	(Lcom/google/android/gms/internal/es;)Lcom/google/android/gms/internal/du;
    //   17: getfield 31	com/google/android/gms/internal/du:f	I
    //   20: bipush 254
    //   22: if_icmpeq +8 -> 30
    //   25: aload_1
    //   26: monitorexit
    //   27: goto +142 -> 169
    //   30: aload_0
    //   31: getfield 12	com/google/android/gms/internal/ew:a	Lcom/google/android/gms/internal/es;
    //   34: invokestatic 35	com/google/android/gms/internal/es:d	(Lcom/google/android/gms/internal/es;)Lcom/google/android/gms/internal/hk;
    //   37: invokevirtual 40	com/google/android/gms/internal/hk:f	()Lcom/google/android/gms/internal/hm;
    //   40: aload_0
    //   41: getfield 12	com/google/android/gms/internal/ew:a	Lcom/google/android/gms/internal/es;
    //   44: invokevirtual 45	com/google/android/gms/internal/hm:a	(Lcom/google/android/gms/internal/ho;)V
    //   47: aload_0
    //   48: getfield 12	com/google/android/gms/internal/ew:a	Lcom/google/android/gms/internal/es;
    //   51: invokestatic 25	com/google/android/gms/internal/es:c	(Lcom/google/android/gms/internal/es;)Lcom/google/android/gms/internal/du;
    //   54: getfield 31	com/google/android/gms/internal/du:f	I
    //   57: bipush 253
    //   59: if_icmpne +64 -> 123
    //   62: new 47	java/lang/StringBuilder
    //   65: dup
    //   66: invokespecial 48	java/lang/StringBuilder:<init>	()V
    //   69: ldc 50
    //   71: invokevirtual 54	java/lang/StringBuilder:append	(Ljava/lang/String;)Ljava/lang/StringBuilder;
    //   74: aload_0
    //   75: getfield 12	com/google/android/gms/internal/ew:a	Lcom/google/android/gms/internal/es;
    //   78: invokestatic 25	com/google/android/gms/internal/es:c	(Lcom/google/android/gms/internal/es;)Lcom/google/android/gms/internal/du;
    //   81: getfield 57	com/google/android/gms/internal/du:c	Ljava/lang/String;
    //   84: invokevirtual 54	java/lang/StringBuilder:append	(Ljava/lang/String;)Ljava/lang/StringBuilder;
    //   87: invokevirtual 61	java/lang/StringBuilder:toString	()Ljava/lang/String;
    //   90: invokestatic 66	com/google/android/gms/internal/hi:d	(Ljava/lang/String;)V
    //   93: aload_0
    //   94: getfield 12	com/google/android/gms/internal/ew:a	Lcom/google/android/gms/internal/es;
    //   97: invokestatic 35	com/google/android/gms/internal/es:d	(Lcom/google/android/gms/internal/es;)Lcom/google/android/gms/internal/hk;
    //   100: aload_0
    //   101: getfield 12	com/google/android/gms/internal/ew:a	Lcom/google/android/gms/internal/es;
    //   104: invokestatic 25	com/google/android/gms/internal/es:c	(Lcom/google/android/gms/internal/es;)Lcom/google/android/gms/internal/du;
    //   107: getfield 57	com/google/android/gms/internal/du:c	Ljava/lang/String;
    //   110: invokevirtual 69	com/google/android/gms/internal/hk:loadUrl	(Ljava/lang/String;)V
    //   113: aload_1
    //   114: monitorexit
    //   115: goto +54 -> 169
    //   118: astore_2
    //   119: aload_1
    //   120: monitorexit
    //   121: aload_2
    //   122: athrow
    //   123: ldc 71
    //   125: invokestatic 66	com/google/android/gms/internal/hi:d	(Ljava/lang/String;)V
    //   128: aload_0
    //   129: getfield 12	com/google/android/gms/internal/ew:a	Lcom/google/android/gms/internal/es;
    //   132: invokestatic 35	com/google/android/gms/internal/es:d	(Lcom/google/android/gms/internal/es;)Lcom/google/android/gms/internal/hk;
    //   135: aload_0
    //   136: getfield 12	com/google/android/gms/internal/ew:a	Lcom/google/android/gms/internal/es;
    //   139: invokestatic 25	com/google/android/gms/internal/es:c	(Lcom/google/android/gms/internal/es;)Lcom/google/android/gms/internal/du;
    //   142: getfield 57	com/google/android/gms/internal/du:c	Ljava/lang/String;
    //   145: invokestatic 76	com/google/android/gms/internal/gw:a	(Ljava/lang/String;)Ljava/lang/String;
    //   148: aload_0
    //   149: getfield 12	com/google/android/gms/internal/ew:a	Lcom/google/android/gms/internal/es;
    //   152: invokestatic 25	com/google/android/gms/internal/es:c	(Lcom/google/android/gms/internal/es;)Lcom/google/android/gms/internal/du;
    //   155: getfield 78	com/google/android/gms/internal/du:d	Ljava/lang/String;
    //   158: ldc 80
    //   160: ldc 82
    //   162: aconst_null
    //   163: invokevirtual 86	com/google/android/gms/internal/hk:loadDataWithBaseURL	(Ljava/lang/String;Ljava/lang/String;Ljava/lang/String;Ljava/lang/String;Ljava/lang/String;)V
    //   166: goto -53 -> 113
    //   169: return
    //
    // Exception table:
    //   from	to	target	type
    //   10	121	118	finally
    //   123	166	118	finally
  }
}

/* Location:           M:\Google Play\APKtoJava_RC2\tools\classes-dex2jar.jar
 * Qualified Name:     com.google.android.gms.internal.ew
 * JD-Core Version:    0.6.0
 */