package com.google.android.gms.internal;

import android.content.ServiceConnection;

public class ki
  implements ServiceConnection
{
  public ki(kh paramkh)
  {
  }

  // ERROR //
  public void onServiceConnected(android.content.ComponentName paramComponentName, android.os.IBinder paramIBinder)
  {
    // Byte code:
    //   0: aload_0
    //   1: getfield 12	com/google/android/gms/internal/ki:a	Lcom/google/android/gms/internal/kh;
    //   4: getfield 22	com/google/android/gms/internal/kh:a	Lcom/google/android/gms/internal/kg;
    //   7: invokestatic 27	com/google/android/gms/internal/kg:a	(Lcom/google/android/gms/internal/kg;)Ljava/util/HashMap;
    //   10: astore_3
    //   11: aload_3
    //   12: monitorenter
    //   13: aload_0
    //   14: getfield 12	com/google/android/gms/internal/ki:a	Lcom/google/android/gms/internal/kh;
    //   17: aload_2
    //   18: invokestatic 30	com/google/android/gms/internal/kh:a	(Lcom/google/android/gms/internal/kh;Landroid/os/IBinder;)Landroid/os/IBinder;
    //   21: pop
    //   22: aload_0
    //   23: getfield 12	com/google/android/gms/internal/ki:a	Lcom/google/android/gms/internal/kh;
    //   26: aload_1
    //   27: invokestatic 33	com/google/android/gms/internal/kh:a	(Lcom/google/android/gms/internal/kh;Landroid/content/ComponentName;)Landroid/content/ComponentName;
    //   30: pop
    //   31: aload_0
    //   32: getfield 12	com/google/android/gms/internal/ki:a	Lcom/google/android/gms/internal/kh;
    //   35: invokestatic 36	com/google/android/gms/internal/kh:a	(Lcom/google/android/gms/internal/kh;)Ljava/util/HashSet;
    //   38: invokevirtual 42	java/util/HashSet:iterator	()Ljava/util/Iterator;
    //   41: astore 7
    //   43: aload 7
    //   45: invokeinterface 48 1 0
    //   50: ifeq +28 -> 78
    //   53: aload 7
    //   55: invokeinterface 52 1 0
    //   60: checkcast 54	com/google/android/gms/internal/jz
    //   63: aload_1
    //   64: aload_2
    //   65: invokevirtual 56	com/google/android/gms/internal/jz:onServiceConnected	(Landroid/content/ComponentName;Landroid/os/IBinder;)V
    //   68: goto -25 -> 43
    //   71: astore 4
    //   73: aload_3
    //   74: monitorexit
    //   75: aload 4
    //   77: athrow
    //   78: aload_0
    //   79: getfield 12	com/google/android/gms/internal/ki:a	Lcom/google/android/gms/internal/kh;
    //   82: iconst_1
    //   83: invokestatic 59	com/google/android/gms/internal/kh:a	(Lcom/google/android/gms/internal/kh;I)I
    //   86: pop
    //   87: aload_3
    //   88: monitorexit
    //   89: return
    //
    // Exception table:
    //   from	to	target	type
    //   13	75	71	finally
    //   78	89	71	finally
  }

  // ERROR //
  public void onServiceDisconnected(android.content.ComponentName paramComponentName)
  {
    // Byte code:
    //   0: aload_0
    //   1: getfield 12	com/google/android/gms/internal/ki:a	Lcom/google/android/gms/internal/kh;
    //   4: getfield 22	com/google/android/gms/internal/kh:a	Lcom/google/android/gms/internal/kg;
    //   7: invokestatic 27	com/google/android/gms/internal/kg:a	(Lcom/google/android/gms/internal/kg;)Ljava/util/HashMap;
    //   10: astore_2
    //   11: aload_2
    //   12: monitorenter
    //   13: aload_0
    //   14: getfield 12	com/google/android/gms/internal/ki:a	Lcom/google/android/gms/internal/kh;
    //   17: aconst_null
    //   18: invokestatic 30	com/google/android/gms/internal/kh:a	(Lcom/google/android/gms/internal/kh;Landroid/os/IBinder;)Landroid/os/IBinder;
    //   21: pop
    //   22: aload_0
    //   23: getfield 12	com/google/android/gms/internal/ki:a	Lcom/google/android/gms/internal/kh;
    //   26: aload_1
    //   27: invokestatic 33	com/google/android/gms/internal/kh:a	(Lcom/google/android/gms/internal/kh;Landroid/content/ComponentName;)Landroid/content/ComponentName;
    //   30: pop
    //   31: aload_0
    //   32: getfield 12	com/google/android/gms/internal/ki:a	Lcom/google/android/gms/internal/kh;
    //   35: invokestatic 36	com/google/android/gms/internal/kh:a	(Lcom/google/android/gms/internal/kh;)Ljava/util/HashSet;
    //   38: invokevirtual 42	java/util/HashSet:iterator	()Ljava/util/Iterator;
    //   41: astore 6
    //   43: aload 6
    //   45: invokeinterface 48 1 0
    //   50: ifeq +25 -> 75
    //   53: aload 6
    //   55: invokeinterface 52 1 0
    //   60: checkcast 54	com/google/android/gms/internal/jz
    //   63: aload_1
    //   64: invokevirtual 63	com/google/android/gms/internal/jz:onServiceDisconnected	(Landroid/content/ComponentName;)V
    //   67: goto -24 -> 43
    //   70: astore_3
    //   71: aload_2
    //   72: monitorexit
    //   73: aload_3
    //   74: athrow
    //   75: aload_0
    //   76: getfield 12	com/google/android/gms/internal/ki:a	Lcom/google/android/gms/internal/kh;
    //   79: iconst_2
    //   80: invokestatic 59	com/google/android/gms/internal/kh:a	(Lcom/google/android/gms/internal/kh;I)I
    //   83: pop
    //   84: aload_2
    //   85: monitorexit
    //   86: return
    //
    // Exception table:
    //   from	to	target	type
    //   13	73	70	finally
    //   75	86	70	finally
  }
}

/* Location:           M:\Google Play\APKtoJava_RC2\tools\classes-dex2jar.jar
 * Qualified Name:     com.google.android.gms.internal.ki
 * JD-Core Version:    0.6.0
 */